espresso/__init__.py
espresso/_espresso_problem.py
espresso/_version.py
espresso/capabilities.py
espresso/exceptions.py
espresso/version.py
espresso/contrib/__init__.py
espresso/contrib/active_problems.txt
espresso/contrib/fmm_tomography/__init__.py
espresso/contrib/fmm_tomography/fmm_tomography.py
espresso/contrib/fmm_tomography/datasets/cbmod.txt
espresso/contrib/fmm_tomography/datasets/example1/receivers_InLab_lrt_r36.dat
espresso/contrib/fmm_tomography/datasets/example1/receivers_crossb_nwt_r10.dat
espresso/contrib/fmm_tomography/datasets/example1/sources_InLab_lrt_s500.dat
espresso/contrib/fmm_tomography/datasets/example1/sources_crossb_nwt_s10.dat
espresso/contrib/fmm_tomography/datasets/example1/ttimes.dat
espresso/contrib/fmm_tomography/datasets/example1/ttimes_InLab_lrt_s500_r36.dat
espresso/contrib/fmm_tomography/datasets/example1/ttimes_crossb_nwt_s10_r10.dat
espresso/contrib/fmm_tomography/datasets/example2/gridt_ex1.vtx
espresso/contrib/fmm_tomography/datasets/example2/receivers_ex1.dat
espresso/contrib/fmm_tomography/datasets/example2/sources_ex1.dat
espresso/contrib/fmm_tomography/datasets/example2/ttimes.dat
espresso/contrib/fmm_tomography/datasets/example3/gridi.vtx
espresso/contrib/fmm_tomography/datasets/example3/gridt.vtx
espresso/contrib/fmm_tomography/datasets/example3/gridt_ex2.vtx
espresso/contrib/fmm_tomography/datasets/example3/receivers_ex2.dat
espresso/contrib/fmm_tomography/datasets/example3/sources_ex2.dat
espresso/contrib/fmm_tomography/datasets/example3/ttimes.dat
espresso/contrib/gravity_inversion/__init__.py
espresso/contrib/gravity_inversion/gravity_inversion.py
espresso/contrib/gravity_inversion/data/__init__.py
espresso/contrib/gravity_inversion/data/gravmodel1.txt
espresso/contrib/gravity_inversion/data/testdata.txt
espresso/contrib/magnetotelluric_1D/__init__.py
espresso/contrib/magnetotelluric_1D/magnetotelluric_1D.py
espresso/contrib/magnetotelluric_1D/data/16-A_KN2.dat
espresso/contrib/magnetotelluric_1D/data/__init__.py
geo_espresso-0.4.0.dist-info/licenses/LICENCE
geo_espresso-0.4.0.dist-info/METADATA
geo_espresso-0.4.0.dist-info/WHEEL
geo_espresso-0.4.0.dist-info/top_level.txt
geo_espresso-0.4.0.dist-info/RECORD
